Anti_gravity_qy/__init__.py
anti_gravity_qy-1766739.703.231.dist-info/licenses/LICENSE
anti_gravity_qy-1766739.703.231.dist-info/METADATA
anti_gravity_qy-1766739.703.231.dist-info/WHEEL
anti_gravity_qy-1766739.703.231.dist-info/top_level.txt
anti_gravity_qy-1766739.703.231.dist-info/RECORD
