Metadata-Version: 2.4
Name: Anti-gravity-qy
Version: 1766739.703.231
Summary: High-quality integration for https://antigravity.google/
Home-page: https://antigravity.google/
Author: SuperMaker
Classifier: Programming Language :: Python :: 3
Classifier: License :: OSI Approved :: MIT License
Requires-Python: >=3.6
License-File: LICENSE
Dynamic: author
Dynamic: classifier
Dynamic: description
Dynamic: description-content-type
Dynamic: home-page
Dynamic: license-file
Dynamic: requires-python
Dynamic: summary
